r3po/__init__.py
r3po/jobbuilder.py
r3po/jobrunner.py
r3po-0.2.0.dist-info/METADATA
r3po-0.2.0.dist-info/WHEEL
r3po-0.2.0.dist-info/top_level.txt
r3po-0.2.0.dist-info/RECORD
