Metadata-Version: 2.1
Name: r3po
Version: 0.2.0
Summary: A library built on top of Ray to make embarassingly parallel tasks embarassingly easy
Home-page: https://github.com/lieuzhenghong/r3po
Author: Zhenghong Lieu
Author-email: lieuzhenghong@email.com
License: Apache License 2.0
Platform: UNKNOWN
Requires-Dist: pyyaml (>=5.3.1)
Requires-Dist: ray (>=0.8.7)
